ai2_kit/__init__.py
ai2_kit/algorithm/__init__.py
ai2_kit/algorithm/aos_analysis.py
ai2_kit/algorithm/proton_transfer.py
ai2_kit/algorithm/reweighting.py
ai2_kit/algorithm/uninmr/__init__.py
ai2_kit/algorithm/uninmr/data/__init__.py
ai2_kit/algorithm/uninmr/data/conformer_dataset.py
ai2_kit/algorithm/uninmr/data/cropping_dataset.py
ai2_kit/algorithm/uninmr/data/distance_dataset.py
ai2_kit/algorithm/uninmr/data/key_dataset.py
ai2_kit/algorithm/uninmr/data/lattice_dataset.py
ai2_kit/algorithm/uninmr/data/lmdb_dataset.py
ai2_kit/algorithm/uninmr/data/mask_points_chunk_dataset.py
ai2_kit/algorithm/uninmr/data/mask_points_dataset.py
ai2_kit/algorithm/uninmr/data/normalize_dataset.py
ai2_kit/algorithm/uninmr/data/pad_dataset.py
ai2_kit/algorithm/uninmr/data/remove_hydrogen_dataset.py
ai2_kit/algorithm/uninmr/data/resample_dataset.py
ai2_kit/algorithm/uninmr/data/select_token_dataset.py
ai2_kit/algorithm/uninmr/infer.py
ai2_kit/algorithm/uninmr/losses/__init__.py
ai2_kit/algorithm/uninmr/losses/atom_regloss.py
ai2_kit/algorithm/uninmr/losses/regloss.py
ai2_kit/algorithm/uninmr/losses/unimat.py
ai2_kit/algorithm/uninmr/losses/unimat_rcut.py
ai2_kit/algorithm/uninmr/models/__init__.py
ai2_kit/algorithm/uninmr/models/transformer_encoder_with_pair.py
ai2_kit/algorithm/uninmr/models/unimat.py
ai2_kit/algorithm/uninmr/tasks/__init__.py
ai2_kit/algorithm/uninmr/tasks/unimat.py
ai2_kit/algorithm/uninmr/tasks/unimat_rcut.py
ai2_kit/algorithm/uninmr/tasks/uninmr.py
ai2_kit/algorithm/uninmr/utils/__init__.py
ai2_kit/algorithm/uninmr/utils/data_preparation/__init__.py
ai2_kit/algorithm/uninmr/utils/data_preparation/nmrshiftdb2_2018.py
ai2_kit/algorithm/uninmr/utils/data_preparation/nmrshiftdb2_2024.py
ai2_kit/algorithm/uninmr/utils/data_preparation/qm9nmr.py
ai2_kit/algorithm/uninmr/utils/data_preparation/write_lmdb.py
ai2_kit/algorithm/uninmr/utils/data_scaler.py
ai2_kit/algorithm/uninmr/utils/get_result.py
ai2_kit/algorithm/uninmr/utils/parse.py
ai2_kit/core/__init__.py
ai2_kit-1.0.5.dist-info/LICENSE
ai2_kit-1.0.5.dist-info/METADATA
ai2_kit-1.0.5.dist-info/WHEEL
ai2_kit-1.0.5.dist-info/entry_points.txt
ai2_kit-1.0.5.dist-info/RECORD
