Metadata-Version: 2.1
Name: ai2-kit
Version: 1.0.5
Summary: 
Author: weihong.xu
Author-email: xuweihong.cn@gmail.com
Requires-Python: >=3.9,<4.0
Classifier: Programming Language :: Python :: 3
Classifier: Programming Language :: Python :: 3.9
Classifier: Programming Language :: Python :: 3.10
Classifier: Programming Language :: Python :: 3.11
Classifier: Programming Language :: Python :: 3.12
Provides-Extra: all
Provides-Extra: rpc
Requires-Dist: allpairspy (>=2.5.0,<3.0.0)
Requires-Dist: asaplib (>=0.0.2,<0.0.3) ; extra == "all"
Requires-Dist: ase (>=3.22.1,<4.0.0)
Requires-Dist: cloudpickle (>=2.2.0,<3.0.0)
Requires-Dist: dpdata (==0.2.18)
Requires-Dist: dscribe (==1.2.2) ; extra == "all"
Requires-Dist: fabric (>=2.7.1,<3.0.0)
Requires-Dist: fire (>=0.5.0,<0.6.0)
Requires-Dist: fire-rpc (==0.1.3) ; extra == "all" or extra == "rpc"
Requires-Dist: invoke (>=1.7.3,<2.0.0)
Requires-Dist: ipympl (>=0.9.3,<0.10.0) ; extra == "all"
Requires-Dist: joblib (>=1.2.0,<2.0.0)
Requires-Dist: jupyter-formily (==0.0.7) ; extra == "all"
Requires-Dist: mdanalysis (>=2.4.3,<3.0.0)
Requires-Dist: netcdf4 (>=1.7.1.post1,<2.0.0)
Requires-Dist: numpy (==1.24.3)
Requires-Dist: oh-my-batch (>=0.6.1,<0.7.0)
Requires-Dist: pandas (>=1.5.3,<2.0.0)
Requires-Dist: psutil (>=5.9.8,<6.0.0)
Requires-Dist: pydantic (==2.8.2)
Requires-Dist: ruamel-yaml (>=0.17.21,<0.18.0)
Requires-Dist: scikit-learn (>=1.6.1,<2.0.0)
Requires-Dist: scipy (>=1.13.0,<2.0.0)
Requires-Dist: shortuuid (>=1.0.11,<2.0.0)
Requires-Dist: tabulate (>=0.9.0,<0.10.0)
